tcm/__init__.py
tcm/__main__.py
tcm/app.py
tcm/data.py
tcm/model.py
tcm/tokenizer.py
topic_context_model-0.1.5.dist-info/LICENSE
topic_context_model-0.1.5.dist-info/METADATA
topic_context_model-0.1.5.dist-info/WHEEL
topic_context_model-0.1.5.dist-info/entry_points.txt
topic_context_model-0.1.5.dist-info/top_level.txt
topic_context_model-0.1.5.dist-info/RECORD
