Metadata-Version: 2.1
Name: topic-context-model
Version: 0.1.5
Summary: Topic Context Model (TCM).
Author-email: "J. Nathanael Philipp" <nathanael@philipp.land>
License: GPLv3+
Project-URL: Homepage, https://github.com/jnphilipp/tcm
Project-URL: Bug Tracker, http://github.com/jnphilipp/tcm/issues
Keywords: topic context model,tcm,lda,lsa
Classifier: Development Status :: 5 - Production/Stable
Classifier: Environment :: Console
Classifier: Intended Audience :: Education
Classifier: Intended Audience :: Science/Research
Classifier: License :: OSI Approved :: GNU General Public License v3 or later (GPLv3+)
Classifier: Operating System :: OS Independent
Classifier: Programming Language :: Python
Classifier: Programming Language :: Python :: 3.10
Classifier: Programming Language :: Python :: 3.11
Classifier: Programming Language :: Python :: 3.12
Classifier: Topic :: Scientific/Engineering
Classifier: Topic :: Scientific/Engineering :: Information Analysis
Requires-Python: >=3.10
License-File: LICENSE
Requires-Dist: scipy ~=1.12.0
Requires-Dist: scikit-learn ~=1.4.0
